feltpy/__init__.py
feltpy/feltpy.py
feltpy-0.0.4.dist-info/LICENSE.md
feltpy-0.0.4.dist-info/METADATA
feltpy-0.0.4.dist-info/WHEEL
feltpy-0.0.4.dist-info/top_level.txt
feltpy-0.0.4.dist-info/RECORD
