Metadata-Version: 2.1
Name: feltpy
Version: 0.0.4
Summary: A package for interacting with the API of Felt.com
Author-email: David Moss <davidmoss1221@gmail.com>
Project-URL: Homepage, https://github.com/moss-xyz/feltpy
Project-URL: Bug Tracker, https://github.com/moss-xyz/feltpy/issues
Classifier: Programming Language :: Python :: 3
Classifier: License :: OSI Approved :: MIT License
Classifier: Operating System :: OS Independent
Requires-Python: >=3.7
License-File: LICENSE.md
Requires-Dist: requests
Requires-Dist: geopandas
